titanic_project/__init__.py
titanic_project/predict_module.py
titanic_project/train_module.py
titanic_project/config/__init__.py
titanic_project/config/settings.py
titanic_project/processing/__init__.py
titanic_project/processing/data_processing.py
titanic_project_model-0.0.2.dist-info/METADATA
titanic_project_model-0.0.2.dist-info/WHEEL
titanic_project_model-0.0.2.dist-info/top_level.txt
titanic_project_model-0.0.2.dist-info/RECORD
