Metadata-Version: 2.1
Name: titanic-project-model
Version: 0.0.2
Summary: Example regression model package from Train In Data.
Home-page: https://github.com/LiliyaKazykhanova/titanic-project
Author: Liliya Kazykhanova
Author-email: kazychanowa.liliya@gmail.com
Requires-Python: >=3.8.0
